nxopentse/__init__.py
nxopentse/cad/__init__.py
nxopentse/cad/assemblies.py
nxopentse/cad/code.py
nxopentse/cad/faceted.py
nxopentse/cae/__init__.py
nxopentse/cae/postprocessing.py
nxopentse/cae/preprocessing.py
nxopentse/cae/results_display.py
nxopentse/cae/solving.py
nxopentse/cae/unversal_file.py
nxopentse/tools/__init__.py
nxopentse/tools/excel.py
nxopentse/tools/general.py
nxopentse/tools/vector_arithmetic.py
nxopentse-0.0.1a24.dist-info/licenses/LICENSE
nxopentse-0.0.1a24.dist-info/METADATA
nxopentse-0.0.1a24.dist-info/WHEEL
nxopentse-0.0.1a24.dist-info/top_level.txt
nxopentse-0.0.1a24.dist-info/RECORD
