Metadata-Version: 2.4
Name: nxopentse
Version: 0.0.1a24
Summary: An NXOpen helper package to reuse code in scripts, in order to avoid having all the underlying code in the journals itself.
Author-email: theScriptingEngineer <nxopen@theScriptingEngineer.com>
Maintainer-email: theScriptingEngineer <nxopen@theScriptingEngineer.com>
Project-URL: Documentation, https://nxopentsedocumentation.theScriptingEngineer.com
Project-URL: Repository, https://github.com/theScriptingEngineer/nxopentse
Project-URL: Issues, https://github.com/theScriptingEngineer/nxopentse/issues
Classifier: Programming Language :: Python :: 3
Classifier: License :: OSI Approved :: GNU Affero General Public License v3
Classifier: Operating System :: OS Independent
Requires-Python: >=3.6
License-File: LICENSE
Dynamic: license-file
